env2ini/__init__.py
env2ini/_modidx.py
env2ini/commands.py
env2ini/conda.py
env2ini/constants.py
env2ini/core.py
env2ini/dataclasses.py
env2ini/files.py
env2ini/paths.py
env2ini/rich.py
env2ini/typer.py
env2ini/types.py
env2ini/utils.py
env2ini-0.0.2.dist-info/LICENSE
env2ini-0.0.2.dist-info/METADATA
env2ini-0.0.2.dist-info/WHEEL
env2ini-0.0.2.dist-info/entry_points.txt
env2ini-0.0.2.dist-info/top_level.txt
env2ini-0.0.2.dist-info/RECORD
